{
  "version": "1.00",
  "title": "Beta finished",
  "icon_refresh": {
    "name": "Refresh",
    "format": "png",
    "src": "img/system",
    "url": "https://raw.githubusercontent.com/GuilhermeSantos001/updates_files/master/Refresh.png"
  },
  "files": [{
      "name": "Icon",
      "format": "png",
      "src": "system/updates",
      "url": "https://raw.githubusercontent.com/GuilhermeSantos001/updates_files/master/icon.png",
      "version": "1.00",
      "description": {
        "pt_br": "Icone para teste",
        "en_us": "Icon to test"
      }
    },
    {
      "name": "Icon2",
      "format": "png",
      "src": "system/updates",
      "url": "https://raw.githubusercontent.com/GuilhermeSantos001/updates_files/master/circle.png",
      "version": "1.00",
      "description": {
        "pt_br": "Icone para teste",
        "en_us": "Icon to test"
      }
    }
  ],
  "files_remove": [{
    "name": "Icon",
    "format": "png",
    "src": "system/updates",
    "description": {
      "pt_br": "Removido por falta de uso",
      "en_us": "Removed due to lack of use"
    }
  }]
}